yanpd/__init__.py
yanpd/api_gateway.py
yanpd/neoconnector.py
yanpd/yang_validator.py
yanpd-0.1.0.dist-info/LICENSE
yanpd-0.1.0.dist-info/WHEEL
yanpd-0.1.0.dist-info/METADATA
yanpd-0.1.0.dist-info/RECORD
