Metadata-Version: 2.1
Name: yanpd
Version: 0.1.0
Summary: Yet Another Neo4j Python Driver
License: MIT
Author: Denis
Author-email: d.mulyalin@gmail.com
Requires-Python: >=3.7,<4.0
Classifier: License :: OSI Approved :: MIT License
Classifier: Programming Language :: Python :: 3
Classifier: Programming Language :: Python :: 3.10
Classifier: Programming Language :: Python :: 3.7
Classifier: Programming Language :: Python :: 3.8
Classifier: Programming Language :: Python :: 3.9
Requires-Dist: requests (>=2.27.1,<3.0.0)
Requires-Dist: yangson (>=1.4.13,<2.0.0)
